{
  "url": "https://sonyliv.com",
  "domain": "sonyliv.com",
  "timestamp": "2026-04-06T16:46:54.058801Z",
  "iterations": [
    {
      "url": "https://sonyliv.com",
      "domain": "sonyliv.com",
      "timestamp": "2026-04-06T16:46:54.058801Z",
      "indexeddb": {
        "databases": []
      },
      "network_requests": [
        {
          "url": "https://sonyliv.com/",
          "method": "GET",
          "resource_type": "document",
          "headers": {
            "upgrade-insecure-requests": "1",
            "user-agent": "Mozilla/5.0 (Windows NT 10.0; Win64; x64) AppleWebKit/537.36 (KHTML, like Gecko) Chrome/120.0.0.0 Safari/537.36",
            "sec-ch-ua": "\"Chromium\";v=\"143\", \"Not A(Brand\";v=\"24\"",
            "sec-ch-ua-mobile": "?0",
            "sec-ch-ua-platform": "\"Windows\""
          },
          "post_data": null,
          "response": {
            "status": 301
          }
        },
        {
          "url": "https://www.sonyliv.com/",
          "method": "GET",
          "resource_type": "document",
          "headers": {
            "upgrade-insecure-requests": "1",
            "user-agent": "Mozilla/5.0 (Windows NT 10.0; Win64; x64) AppleWebKit/537.36 (KHTML, like Gecko) Chrome/120.0.0.0 Safari/537.36",
            "sec-ch-ua": "\"Chromium\";v=\"143\", \"Not A(Brand\";v=\"24\"",
            "sec-ch-ua-mobile": "?0",
            "sec-ch-ua-platform": "\"Windows\""
          },
          "post_data": null,
          "response": {
            "status": 403
          }
        }
      ],
      "errors": [],
      "iteration": 1
    },
    {
      "url": "https://sonyliv.com",
      "domain": "sonyliv.com",
      "timestamp": "2026-04-06T16:47:08.219683Z",
      "indexeddb": {
        "databases": []
      },
      "network_requests": [
        {
          "url": "https://sonyliv.com/",
          "method": "GET",
          "resource_type": "document",
          "headers": {
            "upgrade-insecure-requests": "1",
            "user-agent": "Mozilla/5.0 (Windows NT 10.0; Win64; x64) AppleWebKit/537.36 (KHTML, like Gecko) Chrome/120.0.0.0 Safari/537.36",
            "sec-ch-ua": "\"Chromium\";v=\"143\", \"Not A(Brand\";v=\"24\"",
            "sec-ch-ua-mobile": "?0",
            "sec-ch-ua-platform": "\"Windows\""
          },
          "post_data": null,
          "response": {
            "status": 301
          }
        },
        {
          "url": "https://www.sonyliv.com/",
          "method": "GET",
          "resource_type": "document",
          "headers": {
            "upgrade-insecure-requests": "1",
            "user-agent": "Mozilla/5.0 (Windows NT 10.0; Win64; x64) AppleWebKit/537.36 (KHTML, like Gecko) Chrome/120.0.0.0 Safari/537.36",
            "sec-ch-ua": "\"Chromium\";v=\"143\", \"Not A(Brand\";v=\"24\"",
            "sec-ch-ua-mobile": "?0",
            "sec-ch-ua-platform": "\"Windows\""
          },
          "post_data": null,
          "response": {
            "status": 403
          }
        }
      ],
      "errors": [],
      "iteration": 2
    },
    {
      "url": "https://sonyliv.com",
      "domain": "sonyliv.com",
      "timestamp": "2026-04-06T16:47:21.140855Z",
      "indexeddb": {
        "databases": []
      },
      "network_requests": [
        {
          "url": "https://sonyliv.com/",
          "method": "GET",
          "resource_type": "document",
          "headers": {
            "upgrade-insecure-requests": "1",
            "user-agent": "Mozilla/5.0 (Windows NT 10.0; Win64; x64) AppleWebKit/537.36 (KHTML, like Gecko) Chrome/120.0.0.0 Safari/537.36",
            "sec-ch-ua": "\"Chromium\";v=\"143\", \"Not A(Brand\";v=\"24\"",
            "sec-ch-ua-mobile": "?0",
            "sec-ch-ua-platform": "\"Windows\""
          },
          "post_data": null,
          "response": {
            "status": 301
          }
        },
        {
          "url": "https://www.sonyliv.com/",
          "method": "GET",
          "resource_type": "document",
          "headers": {
            "upgrade-insecure-requests": "1",
            "user-agent": "Mozilla/5.0 (Windows NT 10.0; Win64; x64) AppleWebKit/537.36 (KHTML, like Gecko) Chrome/120.0.0.0 Safari/537.36",
            "sec-ch-ua": "\"Chromium\";v=\"143\", \"Not A(Brand\";v=\"24\"",
            "sec-ch-ua-mobile": "?0",
            "sec-ch-ua-platform": "\"Windows\""
          },
          "post_data": null,
          "response": {
            "status": 403
          }
        }
      ],
      "errors": [],
      "iteration": 3
    }
  ],
  "indexeddb": {
    "databases": []
  },
  "network_requests": [
    {
      "url": "https://sonyliv.com/",
      "method": "GET",
      "resource_type": "document",
      "headers": {
        "upgrade-insecure-requests": "1",
        "user-agent": "Mozilla/5.0 (Windows NT 10.0; Win64; x64) AppleWebKit/537.36 (KHTML, like Gecko) Chrome/120.0.0.0 Safari/537.36",
        "sec-ch-ua": "\"Chromium\";v=\"143\", \"Not A(Brand\";v=\"24\"",
        "sec-ch-ua-mobile": "?0",
        "sec-ch-ua-platform": "\"Windows\""
      },
      "post_data": null,
      "response": {
        "status": 301
      }
    },
    {
      "url": "https://www.sonyliv.com/",
      "method": "GET",
      "resource_type": "document",
      "headers": {
        "upgrade-insecure-requests": "1",
        "user-agent": "Mozilla/5.0 (Windows NT 10.0; Win64; x64) AppleWebKit/537.36 (KHTML, like Gecko) Chrome/120.0.0.0 Safari/537.36",
        "sec-ch-ua": "\"Chromium\";v=\"143\", \"Not A(Brand\";v=\"24\"",
        "sec-ch-ua-mobile": "?0",
        "sec-ch-ua-platform": "\"Windows\""
      },
      "post_data": null,
      "response": {
        "status": 403
      }
    }
  ],
  "errors": []
}